flarumpy/__init__.py
flarumpy/flarum.py
flarumpy/py.typed
flarumpy/utils.py
flarumpy/routes/__init__.py
flarumpy/routes/discussions.py
flarumpy/routes/root.py
flarumpy-1.0a2.dist-info/LICENSE
flarumpy-1.0a2.dist-info/WHEEL
flarumpy-1.0a2.dist-info/METADATA
flarumpy-1.0a2.dist-info/RECORD
